word_levenshtein_cpp.cpython-311-darwin.so
word_levenshtein/__init__.py
word_levenshtein/py_api.py
word_levenshtein-0.0.3.dist-info/LICENSE
word_levenshtein-0.0.3.dist-info/METADATA
word_levenshtein-0.0.3.dist-info/WHEEL
word_levenshtein-0.0.3.dist-info/top_level.txt
word_levenshtein-0.0.3.dist-info/RECORD
