Metadata-Version: 2.1
Name: word_levenshtein
Version: 0.0.3
Summary: Levenshtein in C++ for Python
Home-page: https://github.com/wq2012/word_levenshtein
Author: Quan Wang
Author-email: quanw@google.com
Requires-Python: >=3.7
License-File: LICENSE
Provides-Extra: test
Requires-Dist: pytest; extra == "test"
